{
    "persons": [
        {
            "name": "Sergio Goycochea",
            "alternativeNames": [],
            "age": -1,
            "sex": "male",
            "occurences": {
                "total": 1,
                "firstNameOnly": 0,
                "lastNameOnly": 0,
                "fullName": 1,
                "nickname": 0
            },
            "inTitle": false,
            "inIntro": false,
            "_name": {
                "firstname": "Sergio",
                "lastname": "Goycochea",
                "nickname": null,
                "alternative_names": [],
                "academic_title": null,
                "nobility_title_or_rank": null
            },
            "descriptiveTexts": [
                {
                    "text": "Der argentinische Torwart Sergio Goycochea war ja ein richtiger Elfmeterkiller, er hatte in diesem Turnier schon mehrere Strafst\u00f6\u00dfe gehalten."
                }
            ],
            "occupations": [
                {
                    "text": "Elfmeterkiller"
                }
            ],
            "directQuotes": [],
            "quotedInTitle": false,
            "quotedInIntro": false
        },
        {
            "name": "Franz Beckenbauer",
            "alternativeNames": [],
            "age": -1,
            "sex": "male",
            "occurences": {
                "total": 2,
                "firstNameOnly": 1,
                "lastNameOnly": 0,
                "fullName": 1,
                "nickname": 0
            },
            "inTitle": false,
            "inIntro": false,
            "_name": {
                "firstname": "Franz",
                "lastname": "Beckenbauer",
                "nickname": null,
                "alternative_names": [],
                "academic_title": null,
                "nobility_title_or_rank": null
            },
            "descriptiveTexts": [
                {
                    "text": "Unser Teamchef Franz Beckenbauer war eine absolute Respektsperson."
                },
                {
                    "text": "Der Franz sagte immer: \u00bbJungs, denkt dran: rackert! Wir sind hierhergekommen, weil wir Weltmeister werden wollen!\u00ab"
                }
            ],
            "occupations": [
                {
                    "text": "Souver\u00e4nit\u00e4t"
                },
                {
                    "text": "Teamchef"
                },
                {
                    "text": "Respektsperson"
                }
            ],
            "directQuotes": [
                {
                    "text": "Jungs, denkt dran: rackert! Wir sind hierhergekommen, weil wir Weltmeister werden wollen!"
                }
            ],
            "quotedInTitle": false,
            "quotedInIntro": false
        },
        {
            "name": "Jos\u00e9 Serrizuela",
            "alternativeNames": [],
            "age": -1,
            "sex": "male",
            "occurences": {
                "total": 1,
                "firstNameOnly": 0,
                "lastNameOnly": 0,
                "fullName": 1,
                "nickname": 0
            },
            "inTitle": false,
            "inIntro": false,
            "_name": {
                "firstname": "Jos\u00e9",
                "lastname": "Serrizuela",
                "nickname": null,
                "alternative_names": [],
                "academic_title": null,
                "nobility_title_or_rank": null
            },
            "descriptiveTexts": [
                {
                    "text": "Ich stand etwa 40 Meter von Rudi V\u00f6ller und Jos\u00e9 Serrizuela entfernt, als der Schiedsrichter ein Foul pfiff."
                }
            ],
            "occupations": [],
            "directQuotes": [],
            "quotedInTitle": false,
            "quotedInIntro": false
        },
        {
            "name": "Rudi V\u00f6ller",
            "alternativeNames": [],
            "age": -1,
            "sex": "male",
            "occurences": {
                "total": 3,
                "firstNameOnly": 0,
                "lastNameOnly": 0,
                "fullName": 3,
                "nickname": 0
            },
            "inTitle": false,
            "inIntro": false,
            "_name": {
                "firstname": "Rudi",
                "lastname": "V\u00f6ller",
                "nickname": null,
                "alternative_names": [],
                "academic_title": null,
                "nobility_title_or_rank": null
            },
            "descriptiveTexts": [
                {
                    "text": "Ich stand etwa 40 Meter von Rudi V\u00f6ller und Jos\u00e9 Serrizuela entfernt, als der Schiedsrichter ein Foul pfiff."
                },
                {
                    "text": "Es werden immer drei Sch\u00fctzen f\u00fcr ein Spiel festgelegt: Rudi V\u00f6ller \u2013 aber der war ja gefoult worden, und derjenige sollte nie selbst schie\u00dfen."
                },
                {
                    "text": "Rudi V\u00f6ller kam zu mir und sagte: \u00bbSo, den machst du jetzt rein, dann sind wir Weltmeister.\u00ab"
                }
            ],
            "occupations": [],
            "directQuotes": [
                {
                    "text": "So, den machst du jetzt rein, dann sind wir Weltmeister."
                }
            ],
            "quotedInTitle": false,
            "quotedInIntro": false
        },
        {
            "name": "Lothar Matth\u00e4us",
            "alternativeNames": [],
            "age": -1,
            "sex": "male",
            "occurences": {
                "total": 2,
                "firstNameOnly": 0,
                "lastNameOnly": 0,
                "fullName": 2,
                "nickname": 0
            },
            "inTitle": false,
            "inIntro": false,
            "_name": {
                "firstname": "Lothar",
                "lastname": "Matth\u00e4us",
                "nickname": null,
                "alternative_names": [],
                "academic_title": null,
                "nobility_title_or_rank": null
            },
            "descriptiveTexts": [
                {
                    "text": "Dann Lothar Matth\u00e4us \u2013 aber der f\u00fchlte sich nicht gut."
                },
                {
                    "text": "Im Mannschaftshotel teilte ich das Zimmer mit Lothar Matth\u00e4us."
                }
            ],
            "occupations": [],
            "directQuotes": [],
            "quotedInTitle": false,
            "quotedInIntro": false
        },
        {
            "name": "Andreas Brehme",
            "alternativeNames": [],
            "age": -1,
            "sex": "male",
            "occurences": {
                "total": 2,
                "firstNameOnly": 0,
                "lastNameOnly": 0,
                "fullName": 2,
                "nickname": 0
            },
            "inTitle": false,
            "inIntro": true,
            "_name": {
                "firstname": "Andreas",
                "lastname": "Brehme",
                "nickname": null,
                "alternative_names": [],
                "academic_title": null,
                "nobility_title_or_rank": null
            },
            "descriptiveTexts": [
                {
                    "text": "Er schoss eines der wichtigsten Tore der deutschen Fu\u00dfballgeschichte: Andreas Brehme erinnert sich an das WM-Finale 1990 in Rom gegen Argentinien \u2013 und verr\u00e4t, was ihm in der entscheidenden 85."
                },
                {
                    "text": "Anl\u00e4sslich des Todes von Andreas Brehme ver\u00f6ffentlichen wir ihn noch einmal."
                },
                {
                    "text": "Mir war dann sofort klar, dass ich schie\u00dfen musste."
                },
                {
                    "text": "Also ging ich."
                },
                {
                    "text": "Am schlimmsten war, dass die Argentinier den Ball wieder wegschossen, als ich ihn mir zurechtgelegt hatte."
                },
                {
                    "text": "Ich musste ausblenden, dass die Argentinier versuchten, mich zu verunsichern \u2013 und dass die ganze Welt, Millionen von Fernsehzuschauern, auf mich schaute."
                },
                {
                    "text": "Rudi V\u00f6ller kam zu mir und sagte: \u00bbSo, den machst du jetzt rein, dann sind wir Weltmeister.\u00ab"
                },
                {
                    "text": "\u00bbNa, sch\u00f6nen Dank\u00ab, antwortete ich."
                },
                {
                    "text": "Beim Anlauf dachte ich: Ruhig bleiben!"
                },
                {
                    "text": "Dann schoss ich mit rechts."
                },
                {
                    "text": "Als der Ball auf den Innenpfosten zulief, hatte ich eine Schrecksekunde \u2013 aber dann war er drin."
                },
                {
                    "text": "F\u00fcr einen Fu\u00dfballer ist Weltmeister der gr\u00f6\u00dfte Titel, den er erringen kann."
                },
                {
                    "text": "Im Mannschaftshotel teilte ich das Zimmer mit Lothar Matth\u00e4us."
                },
                {
                    "text": "Der war richtig schwer, das Original ist ja aus massivem Gold, ich sch\u00e4tze, der wiegt f\u00fcnf Kilo."
                }
            ],
            "occupations": [
                {
                    "text": "Souver\u00e4nit\u00e4t"
                },
                {
                    "text": "Weltmeister"
                },
                {
                    "text": "Harmonie"
                }
            ],
            "directQuotes": [
                {
                    "text": "Die ganze Welt schaute auf meinen rechten Fu\u00df"
                }
            ],
            "quotedInTitle": false,
            "quotedInIntro": true
        },
        {
            "name": "Klaus Augenthaler",
            "alternativeNames": [],
            "age": -1,
            "sex": "male",
            "occurences": {
                "total": 1,
                "firstNameOnly": 0,
                "lastNameOnly": 0,
                "fullName": 1,
                "nickname": 0
            },
            "inTitle": false,
            "inIntro": false,
            "_name": {
                "firstname": "Klaus",
                "lastname": "Augenthaler",
                "nickname": null,
                "alternative_names": [],
                "academic_title": null,
                "nobility_title_or_rank": null
            },
            "descriptiveTexts": [
                {
                    "text": "Allerdings war uns vorher bereits ein ganz klarer Elfer nach einem Foul an Klaus Augenthaler versagt worden."
                }
            ],
            "occupations": [],
            "directQuotes": [],
            "quotedInTitle": false,
            "quotedInIntro": false
        }
    ]
}